SetSimilaritySearch/__init__.py
SetSimilaritySearch/all_pairs.py
SetSimilaritySearch/search.py
SetSimilaritySearch/utils.py
SetSimilaritySearch-1.0.1.data/scripts/all_pairs.py
SetSimilaritySearch-1.0.1.dist-info/LICENSE
SetSimilaritySearch-1.0.1.dist-info/METADATA
SetSimilaritySearch-1.0.1.dist-info/WHEEL
SetSimilaritySearch-1.0.1.dist-info/top_level.txt
SetSimilaritySearch-1.0.1.dist-info/RECORD
