Metadata-Version: 2.1
Name: SetSimilaritySearch
Version: 1.0.1
Summary: A Python library of set similarity search algorithms
Home-page: https://github.com/ekzhu/SetSimilaritySearch
Author: Eric Zhu
Author-email: ekzhu@cs.toronto.edu
Keywords: set similarity search all pairs
Classifier: Development Status :: 3 - Alpha
Classifier: Intended Audience :: Developers
Classifier: Programming Language :: Python :: 2.7
Classifier: Programming Language :: Python :: 3
Classifier: Programming Language :: Python :: 3.4
Classifier: Programming Language :: Python :: 3.5
Classifier: Programming Language :: Python :: 3.6
Classifier: Programming Language :: Python :: 3.7
License-File: LICENSE
Requires-Dist: numpy
Provides-Extra: test
Requires-Dist: coverage ; extra == 'test'
Requires-Dist: nose ; extra == 'test'
